{"nodes": [{"id": "pub_human_oversight", "label": "Human Oversight Design Patterns That Actually Work", "file_type": "publication", "source_file": "dev/publications/human-oversight-design-patterns.html", "source_location": null, "source_url": null, "captured_at": "2025-10-28", "author": "Dr. Amara Okafor", "contributor": null}, {"id": "concept_oversight_patterns", "label": "Confidence-tiered Review / Two-pane / I-don't-know affordance", "file_type": "concept", "source_file": "dev/publications/human-oversight-design-patterns.html", "source_location": null, "source_url": null, "captured_at": null, "author": null, "contributor": null}], "edges": [{"source": "pub_human_oversight", "target": "concept_oversight_patterns", "relation": "introduces", "confidence": "EXTRACTED", "confidence_score": 1.0, "source_file": "dev/publications/human-oversight-design-patterns.html", "source_location": "L75-L81", "weight": 1.0}, {"source": "pub_human_oversight", "target": "pub_participatory_ethics", "relation": "semantically_similar_to", "confidence": "INFERRED", "confidence_score": 0.8, "source_file": "dev/publications/human-oversight-design-patterns.html", "source_location": null, "weight": 1.0}, {"source": "pub_human_oversight", "target": "pub_safety_evaluations", "relation": "semantically_similar_to", "confidence": "INFERRED", "confidence_score": 0.7, "source_file": "dev/publications/human-oversight-design-patterns.html", "source_location": null, "weight": 1.0}], "hyperedges": []}